[
  {
    "id": "204276",
    "title": "Split Second (Sean King & Michelle Maxwell, #1)",
    "image": "https://d.gr-assets.com/books/1432495543m/204276.jpg",
    "rating": 3.97,
    "ratingCount": 38536,
    "author": "David Baldacci",
    "status": "currently-reading",
    "lastRead": ""
  },
  {
    "id": "16160834",
    "title": "The Cuckoo's Calling (Cormoran Strike, #1)",
    "image": "https://d.gr-assets.com/books/1365988974m/16160834.jpg",
    "rating": 3.82,
    "ratingCount": 269682,
    "author": "Robert Galbraith",
    "status": "currently-reading",
    "lastRead": ""
  },
  {
    "id": "27384556",
    "title": "The Emperor's Revenge (The Oregon Files #11)",
    "image": "https://d.gr-assets.com/books/1452424613m/27384556.jpg",
    "rating": 4.39,
    "ratingCount": 361,
    "author": "Clive Cussler",
    "status": "read",
    "lastRead": "Jun 10, 2016"
  },
  {
    "id": "627984",
    "title": "Stone Cold (Camel Club, #3)",
    "image": "https://d.gr-assets.com/books/1388174968m/627984.jpg",
    "rating": 4.1,
    "ratingCount": 27271,
    "author": "David Baldacci",
    "status": "read",
    "lastRead": "Jun 10, 2016"
  },
  {
    "id": "18007564",
    "title": "The Martian",
    "image": "https://d.gr-assets.com/books/1413706054m/18007564.jpg",
    "rating": 4.39,
    "ratingCount": 393325,
    "author": "Andy Weir",
    "status": "read",
    "lastRead": "Jun 03, 2016"
  },
  {
    "id": "22807486",
    "title": "War Hawk (Tucker Wayne #2)",
    "image": "https://d.gr-assets.com/books/1457315402m/22807486.jpg",
    "rating": 4.19,
    "ratingCount": 924,
    "author": "James Rollins",
    "status": "read",
    "lastRead": "May 29, 2016"
  },
  {
    "id": "556083",
    "title": "Dead Center (Andy Carpenter #5)",
    "image": "https://d.gr-assets.com/books/1388268745m/556083.jpg",
    "rating": 4.03,
    "ratingCount": 2260,
    "author": "David Rosenfelt",
    "status": "read",
    "lastRead": "May 29, 2016"
  },
  {
    "id": "497006",
    "title": "Sudden Death (Andy Carpenter #4)",
    "image": "https://d.gr-assets.com/books/1412176558m/497006.jpg",
    "rating": 4.04,
    "ratingCount": 2053,
    "author": "David Rosenfelt",
    "status": "read",
    "lastRead": "May 26, 2016"
  },
  {
    "id": "6431993",
    "title": "Shadow of Betrayal (Jonathan Quinn, #3)",
    "image": "https://d.gr-assets.com/books/1389614313m/6431993.jpg",
    "rating": 4.06,
    "ratingCount": 1597,
    "author": "Brett Battles",
    "status": "read",
    "lastRead": "May 23, 2016"
  },
  {
    "id": "3055116",
    "title": "The Deceived (Jonathan Quinn, #2)",
    "image": "https://d.gr-assets.com/books/1389241915m/3055116.jpg",
    "rating": 4.07,
    "ratingCount": 2112,
    "author": "Brett Battles",
    "status": "read",
    "lastRead": "May 11, 2016"
  },
  {
    "id": "8279149",
    "title": "Bury the Lead (Andy Carpenter Series, #3)",
    "image": "https://d.gr-assets.com/books/1328323113m/8279149.jpg",
    "rating": 4.03,
    "ratingCount": 2737,
    "author": "David Rosenfelt",
    "status": "read",
    "lastRead": "May 08, 2016"
  },
  {
    "id": "904203",
    "title": "The Cleaner (Jonathan Quinn, #1)",
    "image": "https://d.gr-assets.com/books/1388257658m/904203.jpg",
    "rating": 3.83,
    "ratingCount": 3589,
    "author": "Brett Battles",
    "status": "read",
    "lastRead": "May 03, 2016"
  },
  {
    "id": "15154",
    "title": "The Collectors (Camel Club, #2)",
    "image": "https://d.gr-assets.com/books/1388179838m/15154.jpg",
    "rating": 4,
    "ratingCount": 29301,
    "author": "David Baldacci",
    "status": "read",
    "lastRead": "Apr 24, 2016"
  },
  {
    "id": "18938240",
    "title": "Reliquary",
    "image": "https://d.gr-assets.com/books/1385338155m/18938240.jpg",
    "rating": 4,
    "ratingCount": 27707,
    "author": "Douglas Preston",
    "status": "read",
    "lastRead": "Apr 17, 2016"
  },
  {
    "id": "2087368",
    "title": "The Happiest Days of Our Lives",
    "image": "https://d.gr-assets.com/books/1285531166m/2087368.jpg",
    "rating": 4.01,
    "ratingCount": 908,
    "author": "Wil Wheaton",
    "status": "read",
    "lastRead": "Apr 15, 2016"
  },
  {
    "id": "441068",
    "title": "The Clinic (Alex Delaware, #11)",
    "image": "https://d.gr-assets.com/books/1341254986m/441068.jpg",
    "rating": 3.78,
    "ratingCount": 6881,
    "author": "Jonathan Kellerman",
    "status": "read",
    "lastRead": "Apr 12, 2016"
  },
  {
    "id": "910863",
    "title": "Spin (Spin, #1)",
    "image": "https://d.gr-assets.com/books/1406383726m/910863.jpg",
    "rating": 4,
    "ratingCount": 24558,
    "author": "Robert Charles Wilson",
    "status": "read",
    "lastRead": "Apr 08, 2016"
  },
  {
    "id": "136642",
    "title": "Ice Limit",
    "image": "https://d.gr-assets.com/books/1172082459m/136642.jpg",
    "rating": 3.95,
    "ratingCount": 13087,
    "author": "Douglas Preston",
    "status": "read",
    "lastRead": "Apr 01, 2016"
  },
  {
    "id": "29342254",
    "title": "Apocalypse Machine",
    "image": "https://d.gr-assets.com/books/1456459019m/29342254.jpg",
    "rating": 4.23,
    "ratingCount": 233,
    "author": "Jeremy Robinson",
    "status": "read",
    "lastRead": "Mar 30, 2016"
  },
  {
    "id": "29343812",
    "title": "SEAL of Approval",
    "image": "https://d.gr-assets.com/books/1456486388m/29343812.jpg",
    "rating": 4.25,
    "ratingCount": 69,
    "author": "Jack Silkstone",
    "status": "read",
    "lastRead": "Mar 24, 2016"
  },
  {
    "id": "2177236",
    "title": "Hold Tight",
    "image": "https://d.gr-assets.com/books/1433737434m/2177236.jpg",
    "rating": 3.93,
    "ratingCount": 29952,
    "author": "Harlan Coben",
    "status": "read",
    "lastRead": "Mar 24, 2016"
  },
  {
    "id": "27781683",
    "title": "Passenger 19 (Jammer Davis, #3)",
    "image": "https://d.gr-assets.com/books/1447159126m/27781683.jpg",
    "rating": 4.18,
    "ratingCount": 391,
    "author": "Ward Larsen",
    "status": "read",
    "lastRead": "Mar 19, 2016"
  }
]
